lambda_forge/__init__.py
lambda_forge/codebuild.py
lambda_forge/constants.py
lambda_forge/context.py
lambda_forge/diagram.py
lambda_forge/forge.py
lambda_forge/layers.py
lambda_forge/path.py
lambda_forge/printer.py
lambda_forge/steps.py
lambda_forge/trackers.py
lambda_forge/api_gateway/__init__.py
lambda_forge/api_gateway/rest.py
lambda_forge/api_gateway/wss.py
lambda_forge/builders/__init__.py
lambda_forge/builders/authorizer_builder.py
lambda_forge/builders/docs_builder.py
lambda_forge/builders/file_service.py
lambda_forge/builders/function_builder.py
lambda_forge/builders/layer_builder.py
lambda_forge/builders/project_builder.py
lambda_forge/builders/service_builder.py
lambda_forge/builders/__pycache__/__init__.cpython-39.pyc
lambda_forge/builders/__pycache__/authorizer_builder.cpython-39.pyc
lambda_forge/builders/__pycache__/docs_builder.cpython-39.pyc
lambda_forge/builders/__pycache__/file_service.cpython-39.pyc
lambda_forge/builders/__pycache__/function_builder.cpython-39.pyc
lambda_forge/builders/__pycache__/layer_builder.cpython-39.pyc
lambda_forge/builders/__pycache__/project_builder.cpython-39.pyc
lambda_forge/builders/__pycache__/service_builder.cpython-39.pyc
lambda_forge/builders/services/cognito.py
lambda_forge/builders/services/dynamodb.py
lambda_forge/builders/services/event_bridge.py
lambda_forge/builders/services/kms.py
lambda_forge/builders/services/layers.py
lambda_forge/builders/services/s3.py
lambda_forge/builders/services/secrets_manager.py
lambda_forge/builders/services/sns.py
lambda_forge/builders/services/sqs.py
lambda_forge/builders/services/websockets.py
lambda_forge/live/__init__.py
lambda_forge/live/awsiot.zip
lambda_forge/live/certificates.py
lambda_forge/live/live.py
lambda_forge/live/live_apigtw.py
lambda_forge/live/live_event.py
lambda_forge/live/live_iam.py
lambda_forge/live/live_lambda.py
lambda_forge/live/live_s3.py
lambda_forge/live/live_server.py
lambda_forge/live/live_sns.py
lambda_forge/live/live_sqs.py
lambda_forge-2.2.2.dist-info/LICENSE
lambda_forge-2.2.2.dist-info/METADATA
lambda_forge-2.2.2.dist-info/WHEEL
lambda_forge-2.2.2.dist-info/entry_points.txt
lambda_forge-2.2.2.dist-info/top_level.txt
lambda_forge-2.2.2.dist-info/RECORD
