Metadata-Version: 2.1
Name: lambda-forge
Version: 2.2.2
Summary: Lambda Forge is a framework to help you create lambda functions following a pre-defined structure.
Home-page: UNKNOWN
Author: Guilherme Alves Pimenta
Author-email: guialvespimenta27@gmail.com
License: MIT
Platform: UNKNOWN
License-File: LICENSE
Requires-Dist: attrs ==22.1.0
Requires-Dist: aws-cdk-lib <3.0.0,>=2.0.0
Requires-Dist: constructs <11.0.0,>=10.0.0
Requires-Dist: boto3 ==1.26.59
Requires-Dist: click ==8.1.3
Requires-Dist: pytest <7.0.0
Requires-Dist: pytest-sugar ==1.0.0
Requires-Dist: coverage ==7.2.3
Requires-Dist: python-dotenv ==1.0.1
Requires-Dist: b-aws-websocket-api ==2.0.0
Requires-Dist: requests ==2.31.0
Requires-Dist: AWSIoTPythonSDK ==1.5.4
Requires-Dist: awslambdaric ==2.0.11
Requires-Dist: pyfiglet ==1.0.2
Requires-Dist: inquirerpy ==0.3.4
Requires-Dist: tabulate ==0.9.0
Requires-Dist: diagrams ==0.23.4
Requires-Dist: textual ==0.75.1
Requires-Dist: textual-serve ==1.0.3
